tracy_binary/__init__.py
tracy_binary/__main__.py
tracy_binary/tracy_v0.7.5_linux_x86_64bit
tracy_binary-0.1.2.dist-info/LICENSE
tracy_binary-0.1.2.dist-info/LICENSE-tracy
tracy_binary-0.1.2.dist-info/METADATA
tracy_binary-0.1.2.dist-info/WHEEL
tracy_binary-0.1.2.dist-info/entry_points.txt
tracy_binary-0.1.2.dist-info/RECORD
