Metadata-Version: 2.1
Name: tracy-binary
Version: 0.1.2
Summary: Binary packaging of the Tracy base caller
License: BSD 3-Clause License
Author: Kevin Schmittle
Author-email: kevin@schmittle.net
Requires-Python: >=3.6,<4.0
Classifier: License :: Other/Proprietary License
Classifier: Programming Language :: Python :: 3
Classifier: Programming Language :: Python :: 3.6
Classifier: Programming Language :: Python :: 3.7
Classifier: Programming Language :: Python :: 3.8
Classifier: Programming Language :: Python :: 3.9
Classifier: Programming Language :: Python :: 3.10
Classifier: Programming Language :: Python :: 3.11
Classifier: Programming Language :: Python :: 3.12
